aiorentry/__init__.py
aiorentry/client.py
aiorentry/models.py
aiorentry-0.2.0.dist-info/LICENSE
aiorentry-0.2.0.dist-info/METADATA
aiorentry-0.2.0.dist-info/WHEEL
aiorentry-0.2.0.dist-info/RECORD
