Metadata-Version: 2.3
Name: aiorentry
Version: 0.2.0
Summary: Asynchronous client for https://rentry.co/ (https://rentry.org/)
License: MIT
Keywords: markdown,pastebin,rentry
Author: froosty
Author-email: froosty.gh@gmail.com
Requires-Python: >=3.10,<4.0
Classifier: Intended Audience :: Developers
Classifier: License :: OSI Approved :: MIT License
Classifier: Programming Language :: Python :: 3
Classifier: Programming Language :: Python :: 3.10
Classifier: Programming Language :: Python :: 3.11
Classifier: Programming Language :: Python :: 3.12
Classifier: Programming Language :: Python :: 3.13
Classifier: Topic :: Text Processing :: Markup
Requires-Dist: aiohttp (>=3.9.0)
Requires-Dist: typing-extensions (>=4.12.2,<5.0.0)
Requires-Dist: yarl (==1.18.3)
Project-URL: Repository, https://github.com/froosty/aiorentry
